iconer/__init__.py
iconer/attribute.py
iconer/command.py
iconer/download.py
iconer-0.1.dist-info/LICENSE
iconer-0.1.dist-info/METADATA
iconer-0.1.dist-info/WHEEL
iconer-0.1.dist-info/entry_points.txt
iconer-0.1.dist-info/top_level.txt
iconer-0.1.dist-info/zip-safe
iconer-0.1.dist-info/RECORD
