Metadata-Version: 2.1
Name: iconer
Version: 0.1
Summary: Rich favicons, ICO and PNG formats.
Home-page: https://github.com/podboy/favicons/
Author: Mingzhe Zou
Author-email: zoumingzhe@outlook.com
License: MIT
Project-URL: Source Code, https://github.com/podboy/favicons/
Project-URL: Bug Tracker, https://github.com/podboy/favicons/issues
Project-URL: Documentation, https://github.com/podboy/favicons/
Keywords: xarg,icon,favicon,ico,png
Platform: any
Classifier: Programming Language :: Python
Classifier: Programming Language :: Python :: 3
License-File: LICENSE
Requires-Dist: favicon
Requires-Dist: xarg-python (>=1.5)
